.coveragerc
.gitignore
.readthedocs.yml
AUTHORS.rst
CHANGELOG.rst
LICENSE.txt
README.rst
notebook.ipynb
pyproject.toml
requirements.txt
setup.cfg
setup.py
tox.ini
docs/Makefile
docs/authors.rst
docs/changelog.rst
docs/conf.py
docs/contributing.rst
docs/index.rst
docs/license.rst
docs/readme.rst
docs/requirements.txt
docs/_static/.gitignore
src/sde_py_lib/client.py
src/sde_py_lib/model.py
src/sde_py_lib.egg-info/PKG-INFO
src/sde_py_lib.egg-info/SOURCES.txt
src/sde_py_lib.egg-info/dependency_links.txt
src/sde_py_lib.egg-info/not-zip-safe
src/sde_py_lib.egg-info/requires.txt
src/sde_py_lib.egg-info/top_level.txt
tests/conftest.py
tests/test_client.py
tests/test_skeleton.py