Metadata-Version: 2.4
Name: sde-py-lib
Version: 0.0.3
Summary: A Python SDK for interaction with the Synopses Data Engine
Home-page: https://github.com/petroud/SDE-py-lib
Author: Dimitris Petrou
Author-email: petroudimitris@outlook.com
License: MIT
Project-URL: SDE, https://github.com/petroud/SDE-E
Platform: any
Classifier: Development Status :: 4 - Beta
Classifier: Programming Language :: Python
Requires-Python: >=3.8
License-File: LICENSE.txt
Requires-Dist: importlib-metadata; python_version < "3.8"
Provides-Extra: testing
Requires-Dist: setuptools; extra == "testing"
Requires-Dist: pytest; extra == "testing"
Requires-Dist: pytest-cov; extra == "testing"
Requires-Dist: kafka; extra == "testing"
Dynamic: license-file
